plover_splits/__init__.py
plover_splits/system.py
plover_splits-0.0.1.dist-info/METADATA
plover_splits-0.0.1.dist-info/RECORD
plover_splits-0.0.1.dist-info/WHEEL
plover_splits-0.0.1.dist-info/entry_points.txt
plover_splits-0.0.1.dist-info/top_level.txt
plover_splits-0.0.1.dist-info/zip-safe
